pygfx/__init__.py
pygfx/__main__.py
pygfx/_version.py
pygfx/__pyinstaller/__init__.py
pygfx/__pyinstaller/conftest.py
pygfx/__pyinstaller/hook-pygfx.py
pygfx/__pyinstaller/test_pygfx.py
pygfx/animation/__init__.py
pygfx/animation/animation_action.py
pygfx/animation/animation_clip.py
pygfx/animation/animation_mixer.py
pygfx/animation/clock.py
pygfx/animation/interpolant.py
pygfx/animation/keyframe_track.py
pygfx/cameras/__init__.py
pygfx/cameras/_base.py
pygfx/cameras/_orthographic.py
pygfx/cameras/_perspective.py
pygfx/controllers/__init__.py
pygfx/controllers/_base.py
pygfx/controllers/_fly.py
pygfx/controllers/_orbit.py
pygfx/controllers/_panzoom.py
pygfx/controllers/_trackball.py
pygfx/data_files/Humor-Sans.ttf
pygfx/data_files/NotoSans-Regular.ttf
pygfx/data_files/NotoSansArabic-Regular.ttf
pygfx/data_files/NotoSansDevanagari-Regular.ttf
pygfx/data_files/NotoSansSymbols-Regular.ttf
pygfx/data_files/__init__.py
pygfx/data_files/noto_default_index.json
pygfx/geometries/__init__.py
pygfx/geometries/_base.py
pygfx/geometries/_box.py
pygfx/geometries/_compat.py
pygfx/geometries/_cylinder.py
pygfx/geometries/_plane.py
pygfx/geometries/_polyhedron.py
pygfx/geometries/_sphere.py
pygfx/geometries/_toroidal.py
pygfx/geometries/utils.py
pygfx/helpers/__init__.py
pygfx/helpers/_axes.py
pygfx/helpers/_box.py
pygfx/helpers/_gizmo.py
pygfx/helpers/_grid.py
pygfx/helpers/_lights.py
pygfx/helpers/_skeleton.py
pygfx/helpers/_stats.py
pygfx/materials/__init__.py
pygfx/materials/_background.py
pygfx/materials/_base.py
pygfx/materials/_compat.py
pygfx/materials/_grid.py
pygfx/materials/_image.py
pygfx/materials/_line.py
pygfx/materials/_mesh.py
pygfx/materials/_points.py
pygfx/materials/_text.py
pygfx/materials/_volume.py
pygfx/objects/__init__.py
pygfx/objects/_base.py
pygfx/objects/_events.py
pygfx/objects/_instanced.py
pygfx/objects/_lights.py
pygfx/objects/_more.py
pygfx/objects/_ruler.py
pygfx/objects/_skins.py
pygfx/objects/_text.py
pygfx/renderers/__init__.py
pygfx-0.15.3.dist-info/entry_points.txt
pygfx-0.15.3.dist-info/licenses/LICENSE
pygfx-0.15.3.dist-info/WHEEL
pygfx-0.15.3.dist-info/METADATA
pygfx-0.15.3.dist-info/RECORD
