Metadata-Version: 2.4
Name: pygfx
Version: 0.15.3
Summary: Powerful and versatile visualization for Python
Keywords: render-engine,graphics,3d,science,visualization ,webgpu,wgpu
Author: Almar Klein, Korijn van Golen
Requires-Python: >= 3.10
License-File: LICENSE
Requires-Dist: rendercanvas >= 2.2, !=2.3.0, !=2.4.0
Requires-Dist: wgpu >=0.24.0, <0.30
Requires-Dist: pylinalg >=0.6.8,<0.7.0
Requires-Dist: numpy
Requires-Dist: freetype-py
Requires-Dist: uharfbuzz
Requires-Dist: jinja2
Requires-Dist: hsluv >=5
Requires-Dist: pygfx[lint, tests, examples, docs] ; extra == "dev"
Requires-Dist: sphinx>7.2 ; extra == "docs"
Requires-Dist: sphinx_rtd_theme ; extra == "docs"
Requires-Dist: sphinx-gallery ; extra == "docs"
Requires-Dist: matplotlib ; extra == "docs"
Requires-Dist: imageio[pyav] ; extra == "docs"
Requires-Dist: scikit-image ; extra == "docs"
Requires-Dist: trimesh ; extra == "docs"
Requires-Dist: gltflib ; extra == "docs"
Requires-Dist: imgui-bundle >=1.92 ; extra == "docs"
Requires-Dist: httpx ; extra == "docs"
Requires-Dist: pytest ; extra == "examples"
Requires-Dist: imageio[pyav] ; extra == "examples"
Requires-Dist: scikit-image ; extra == "examples"
Requires-Dist: trimesh ; extra == "examples"
Requires-Dist: gltflib ; extra == "examples"
Requires-Dist: imgui-bundle >=1.92 ; extra == "examples"
Requires-Dist: httpx ; extra == "examples"
Requires-Dist: ruff ; extra == "lint"
Requires-Dist: pytest ; extra == "tests"
Requires-Dist: psutil ; extra == "tests"
Requires-Dist: trimesh ; extra == "tests"
Requires-Dist: httpx ; extra == "tests"
Requires-Dist: gltflib ; extra == "tests"
Requires-Dist: imageio ; extra == "tests"
Project-URL: Documentation, https://docs.pygfx.org
Project-URL: Homepage, https://pygfx.org
Project-URL: Repository, https://github.com/pygfx/pygfx
Provides-Extra: dev
Provides-Extra: docs
Provides-Extra: examples
Provides-Extra: lint
Provides-Extra: tests
